simpypi
