Metadata-Version: 1.0
Name: simpypi
Version: 0.1.2
Summary: Simple pypi package
Home-page: http://k0s.org/mozilla/hg/simpypi
Author: Jeff Hammel
Author-email: jhammel@mozilla.com
License: MPL
Platform: UNKNOWN
